fairseq2/__init__.py
fairseq2/gang.py
fairseq2/memory.py
fairseq2/py.typed
fairseq2/typing.py
fairseq2/assets/__init__.py
fairseq2/assets/card.py
fairseq2/assets/card_storage.py
fairseq2/assets/download_manager.py
fairseq2/assets/error.py
fairseq2/assets/store.py
fairseq2/assets/cards/nllb-200.yaml
fairseq2/assets/cards/nllb-200_dense_1b.yaml
fairseq2/assets/cards/nllb-200_dense_3b.yaml
fairseq2/assets/cards/nllb-200_dense_distill_1b.yaml
fairseq2/assets/cards/nllb-200_dense_distill_600m.yaml
fairseq2/assets/cards/s2t_conformer_covost_st_en_de.yaml
fairseq2/assets/cards/s2t_conformer_rel_pos_covost_st_en_de.yaml
fairseq2/assets/cards/s2t_transformer_covost_st_en_de.yaml
fairseq2/assets/cards/s2t_transformer_mustc_asr_de_s.yaml
fairseq2/assets/cards/s2t_transformer_mustc_asr_es_s.yaml
fairseq2/assets/cards/s2t_transformer_mustc_asr_jt_m.yaml
fairseq2/assets/cards/s2t_transformer_mustc_st_de_s.yaml
fairseq2/assets/cards/s2t_transformer_mustc_st_jt_m.yaml
fairseq2/data/__init__.py
fairseq2/data/audio.py
fairseq2/data/cstring.py
fairseq2/data/data_pipeline.py
fairseq2/data/typing.py
fairseq2/data/vocabulary_info.py
fairseq2/data/text/__init__.py
fairseq2/data/text/converters.py
fairseq2/data/text/multilingual_text_tokenizer.py
fairseq2/data/text/sentencepiece.py
fairseq2/data/text/text_reader.py
fairseq2/data/text/text_tokenizer.py
fairseq2/generation/__init__.py
fairseq2/generation/beam_search.py
fairseq2/generation/logits_processor.py
fairseq2/generation/sequence_generator.py
fairseq2/generation/text.py
fairseq2/models/__init__.py
fairseq2/models/decoder.py
fairseq2/models/encoder_decoder.py
fairseq2/models/feature_extractor.py
fairseq2/models/seq2seq.py
fairseq2/models/sequence.py
fairseq2/models/conformer/__init__.py
fairseq2/models/conformer/block.py
fairseq2/models/conformer/convolution.py
fairseq2/models/nllb/__init__.py
fairseq2/models/nllb/builder.py
fairseq2/models/nllb/loader.py
fairseq2/models/nllb/tokenizer.py
fairseq2/models/s2t_transformer/__init__.py
fairseq2_patch-0.1.1.dist-info/LICENSE
fairseq2_patch-0.1.1.dist-info/METADATA
fairseq2_patch-0.1.1.dist-info/WHEEL
fairseq2_patch-0.1.1.dist-info/top_level.txt
fairseq2_patch-0.1.1.dist-info/RECORD
