Metadata-Version: 2.1
Name: fairseq2-patch
Version: 0.1.1
Summary: FAIR Sequence Modeling Toolkit
Home-page: https://github.com/facebookresearch/fairseq2
Author: Fundamental AI Research (FAIR) at Meta
License: MIT
Keywords: machine learning
Classifier: Development Status :: 4 - Beta
Classifier: Intended Audience :: Developers
Classifier: Intended Audience :: Science/Research
Classifier: License :: OSI Approved :: MIT License
Classifier: Programming Language :: Python :: 3
Classifier: Programming Language :: Python :: 3.8
Classifier: Programming Language :: Python :: 3.9
Classifier: Programming Language :: Python :: 3.10
Classifier: Programming Language :: Python :: 3.11
Classifier: Topic :: Scientific/Engineering :: Artificial Intelligence
Requires-Python: >=3.8
License-File: LICENSE
Requires-Dist: fairseq2n-patch ==0.1.1
Requires-Dist: jiwer ~=3.0
Requires-Dist: numpy ~=1.23
Requires-Dist: overrides ~=7.3
Requires-Dist: packaging ~=23.1
Requires-Dist: pyyaml ~=6.0
Requires-Dist: sacrebleu ~=2.3
Requires-Dist: torch >=1.12.1
Requires-Dist: torcheval ~=0.0.6
Requires-Dist: tqdm ~=4.62
Requires-Dist: typing-extensions ~=4.3 ; python_version < "3.10"
